ptars-0.0.9.dist-info/METADATA
ptars-0.0.9.dist-info/WHEEL
ptars-0.0.9.dist-info/licenses/LICENSE
ptars.libs/libgcc_s-262c4f60.so.1
ptars/__init__.py
ptars/_lib.abi3.so
ptars/internal.py
ptars-0.0.9.dist-info/RECORD
