Metadata-Version: 2.4
Name: ptars
Version: 0.0.9
Classifier: Development Status :: 4 - Beta
Classifier: License :: OSI Approved :: Apache Software License
Classifier: Natural Language :: English
Classifier: Operating System :: POSIX :: Linux
Classifier: Programming Language :: Python :: 3 :: Only
Classifier: Programming Language :: Python :: 3.10
Classifier: Programming Language :: Python :: 3.11
Classifier: Programming Language :: Python :: 3.12
Classifier: Programming Language :: Python :: 3.13
Classifier: Programming Language :: Python :: 3.14
Classifier: Programming Language :: Rust
Requires-Dist: googleapis-common-protos
Requires-Dist: protobuf
Requires-Dist: pyarrow
License-File: LICENSE
Summary: Convert from protobuf to arrow and back in rust
Keywords: apache-arrow,data,protobuf,rust
Author-email: 0x26res <0x26res@gmail.com.co>
Maintainer-email: 0x26res <0x26res@gmail.com>
License: Apache-2.0
Requires-Python: >=3.10, <4.0
Project-URL: documentation, https://ptars.readthedocs.io/en/latest/
Project-URL: repository, https://github.com/0x26res/ptars
